veri_agents_playground/__init__.py
veri_agents_playground/cli.py
veri_agents_playground/ingest.py
veri_agents_playground/run_api.py
veri_agents_playground/agents/__init__.py
veri_agents_playground/agents/access.py
veri_agents_playground/agents/persistence.py
veri_agents_playground/agents/workflow.py
veri_agents_playground/agents/workspace.py
veri_agents_playground/agents/knowledgebases/generic.py
veri_agents_playground/agents/knowledgebases/knowledgebases_store.py
veri_agents_playground/agents/knowledgebases/source_retriever.py
veri_agents_playground/agents/knowledgebases/veritone_support.py
veri_agents_playground/agents/providers/__init__.py
veri_agents_playground/agents/providers/knowledgebase.py
veri_agents_playground/agents/providers/llm.py
veri_agents_playground/agents/providers/persistence.py
veri_agents_playground/agents/providers/system.py
veri_agents_playground/agents/providers/tool.py
veri_agents_playground/agents/providers/workflow.py
veri_agents_playground/agents/providers/workspace.py
veri_agents_playground/agents/tools/aiware.py
veri_agents_playground/agents/tools/ask_human.py
veri_agents_playground/agents/tools/dmh.py
veri_agents_playground/agents/tools/knowledge_retrieval.py
veri_agents_playground/agents/tools/veritone_support.py
veri_agents_playground/agents/tools/veritone_voice.py
veri_agents_playground/agents/workflows/answer.py
veri_agents_playground/agents/workflows/assert.py
veri_agents_playground/agents/workflows/dmh_video_search.py
veri_agents_playground/agents/workflows/extract.py
veri_agents_playground/agents/workflows/extract_legacy.py
veri_agents_playground/agents/workflows/qa.py
veri_agents_playground/agents/workflows/utils.py
veri_agents_playground/agents/workflows/veritone_aiware.py
veri_agents_playground/agents/workflows/veritone_dag.py
veri_agents_playground/agents/workflows/veritone_dag.txt
veri_agents_playground/agents/workflows/veritone_omni.py
veri_agents_playground/agents/workflows/veritone_support.py
veri_agents_playground-0.1.0.dist-info/METADATA
veri_agents_playground-0.1.0.dist-info/WHEEL
veri_agents_playground-0.1.0.dist-info/entry_points.txt
veri_agents_playground-0.1.0.dist-info/RECORD
