Metadata-Version: 2.4
Name: veri-agents-playground
Version: 0.1.0
Author-email: Markus Toman <mtoman@veritone.com>
Requires-Python: <3.13,>=3.12
Requires-Dist: aiohttp<4.0.0,>=3.10.6
Requires-Dist: bs4<1.0.0,>=0.0.2
Requires-Dist: fastembed<1.0.0,>=0.4.1
Requires-Dist: gql>=3.5.2
Requires-Dist: langchain-aws>=0.2.7
Requires-Dist: langchain-community>=0.2.12
Requires-Dist: langchain-mcp-adapters>=0.0.5
Requires-Dist: pydantic-settings<3.0.0,>=2.4.0
Requires-Dist: python-dotenv<2.0.0,>=1.0.1
Requires-Dist: veri-agents-aiware[all]
Requires-Dist: veri-agents-api[fastapi]
Requires-Dist: veri-agents-knowledgebase[all]
Provides-Extra: dev
Requires-Dist: ipykernel<7.0.0,>=6.29.5; extra == 'dev'
